aplr_cpp.cpython-313-darwin.so
aplr/__init__.py
aplr/aplr.py
aplr-10.20.1.dist-info/RECORD
aplr-10.20.1.dist-info/WHEEL
aplr-10.20.1.dist-info/top_level.txt
aplr-10.20.1.dist-info/METADATA
aplr-10.20.1.dist-info/licenses/LICENSE
